{"description":"","public":false,"created_at":"2018-05-22T12:07:10.000-03:00","files":["style-color-03.css"],"owner":"slowaways","div":"<div id=\"gist89709724\" class=\"gist\">\n    <div class=\"gist-file\">\n      <div class=\"gist-data\">\n        <div class=\"js-gist-file-update-container js-task-list-container file-box\">\n  <div id=\"file-style-color-03-css\" class=\"file\">\n    \n\n  <div itemprop=\"text\" class=\"blob-wrapper data type-css\">\n      <table class=\"highlight tab-size js-file-line-container\" data-tab-size=\"8\">\n      <tr>\n        <td id=\"file-style-color-03-css-L1\" class=\"blob-num js-line-number\" data-line-number=\"1\"></td>\n        <td id=\"file-style-color-03-css-LC1\" class=\"blob-code blob-code-inner js-file-line\"><span class=\"pl-e\">.text-brand</span> {</td>\n      </tr>\n      <tr>\n        <td id=\"file-style-color-03-css-L2\" class=\"blob-num js-line-number\" data-line-number=\"2\"></td>\n        <td id=\"file-style-color-03-css-LC2\" class=\"blob-code blob-code-inner js-file-line\">  <span class=\"pl-c1\"><span class=\"pl-c1\">color</span></span>: <span class=\"pl-c1\">#a2aa33</span>;</td>\n      </tr>\n      <tr>\n        <td id=\"file-style-color-03-css-L3\" class=\"blob-num js-line-number\" data-line-number=\"3\"></td>\n        <td id=\"file-style-color-03-css-LC3\" class=\"blob-code blob-code-inner js-file-line\">}</td>\n      </tr>\n      <tr>\n        <td id=\"file-style-color-03-css-L4\" class=\"blob-num js-line-number\" data-line-number=\"4\"></td>\n        <td id=\"file-style-color-03-css-LC4\" class=\"blob-code blob-code-inner js-file-line\"><span class=\"pl-e\">.bg-brand</span> {</td>\n      </tr>\n      <tr>\n        <td id=\"file-style-color-03-css-L5\" class=\"blob-num js-line-number\" data-line-number=\"5\"></td>\n        <td id=\"file-style-color-03-css-LC5\" class=\"blob-code blob-code-inner js-file-line\">  <span class=\"pl-c1\"><span class=\"pl-c1\">background</span></span>: <span class=\"pl-c1\">#a2aa33</span>;</td>\n      </tr>\n      <tr>\n        <td id=\"file-style-color-03-css-L6\" class=\"blob-num js-line-number\" data-line-number=\"6\"></td>\n        <td id=\"file-style-color-03-css-LC6\" class=\"blob-code blob-code-inner js-file-line\">}</td>\n      </tr>\n</table>\n\n\n  </div>\n\n  </div>\n</div>\n\n      </div>\n      <div class=\"gist-meta\">\n        <a href=\"https://gist.github.com/slowaways/3d1b0710a65107e02ee1d1233dadc3f9/raw/6e57c15b0b6a4eb80f3579d88d036ad9eb39abc9/style-color-03.css\" style=\"float:right\">view raw</a>\n        <a href=\"https://gist.github.com/slowaways/3d1b0710a65107e02ee1d1233dadc3f9#file-style-color-03-css\">style-color-03.css</a>\n        hosted with &#10084; by <a href=\"https://github.com\">GitHub</a>\n      </div>\n    </div>\n</div>\n","stylesheet":"https://assets-cdn.github.com/assets/gist-embed-8c6ade0d3779da026346afb9bf324f67.css"}
